Workbook

Sheet rakuten_view
A1: date | B1: jan | C1: sku | D1: rakuten_item_id | E1: item_name | F1: as_of_date | G1: selling_price_latest | H1: stock_quantity_latest | I1: review_rating_latest | J1: review_count_latest | K1: genre_rank_latest | L1: search_rank_keyword_latest | M1: search_rank_position_latest | N1: sales_net_7d | O1: units_sold_7d | P1: sessions_7d | Q1: orders_7d | R1: cvr_7d | S1: aov_7d | T1: discount_amount_7d | U1: points_amount_7d | V1: coupon_issue_fee_7d | W1: ad_spend_7d | X1: ad_sales_7d | Y1: roas_7d | Z1: tacos_7d | AA1: platform_fee_7d | AB1: shipping_cost_7d | AC1: other_fee_7d | AD1: cogs_7d | AE1: gross_profit_7d | AF1: profit_margin_7d | AG1: effective_revenue_per_unit_7d | AH1: sales_net_30d | AI1: units_sold_30d | AJ1: sessions_30d | AK1: orders_30d | AL1: cvr_30d | AM1: aov_30d | AN1: discount_amount_30d | AO1: points_amount_30d | AP1: coupon_issue_fee_30d | AQ1: ad_spend_30d | AR1: ad_sales_30d | AS1: roas_30d | AT1: tacos_30d | AU1: platform_fee_30d | AV1: shipping_cost_30d | AW1: other_fee_30d | AX1: cogs_30d | AY1: gross_profit_30d | AZ1: profit_margin_30d | BA1: effective_revenue_per_unit_30d
A2: 日付 | B2: JAN | C2: SKU | D2: 楽天商品ID | E2: 商品名 | F2: 基準日 | G2: 販売価格(込/最新) | H2: 在庫数(最新) | I2: 評価(最新) | J2: レビュー数(最新) | K2: ジャンル順位(最新) | L2: 検索KW(最新) | M2: 検索順位(最新) | N2: 売上(込)_7日 | O2: 販売数_7日 | P2: アクセス_7日 | Q2: 注文件数_7日 | R2: CVR_7日 | S2: 客単価_7日 | T2: 値引額_7日 | U2: ポイント原資_7日 | V2: クーポン手数料_7日 | W2: 広告費_7日 | X2: 広告売上_7日 | Y2: ROAS_7日 | Z2: TACoS_7日 | AA2: 手数料_7日 | AB2: 送料負担_7日 | AC2: その他費_7日 | AD2: 原価_7日 | AE2: 粗利(税込)_7日 | AF2: 粗利率_7日 | AG2: 実質売上/個_7日 | AH2: 売上(込)_30日 | AI2: 販売数_30日 | AJ2: アクセス_30日 | AK2: 注文件数_30日 | AL2: CVR_30日 | AM2: 客単価_30日 | AN2: 値引額_30日 | AO2: ポイント原資_30日 | AP2: クーポン手数料_30日 | AQ2: 広告費_30日 | AR2: 広告売上_30日 | AS2: ROAS_30日 | AT2: TACoS_30日 | AU2: 手数料_30日 | AV2: 送料負担_30日 | AW2: その他費_30日 | AX2: 原価_30日 | AY2: 粗利(税込)_30日 | AZ2: 粗利率_30日 | BA2: 実質売上/個_30日
A3: {=rakuten_fact_daily_raw!A3} -> 45962 | B3: =IFERROR(__xludf.DUMMYFUNCTION("SORT(UNIQUE(FILTER(rakuten_fact_daily_raw!B3:B1000, rakuten_fact_daily_raw!B3:B1000<>""""))) "),4.512345678001E12) -> 4512345678001 | C3: {=IF(B3:B1000="",,XLOOKUP(B3:B1000, rakuten_fact_daily_raw!B3:B1000, rakuten_fact_daily_raw!C3:C1000, ""))} -> SKU-A001 | D3: {=IF(B3:B1000="",, IFERROR( XLOOKUP(B3:B1000, rakuten_primary_map!A:A, rakuten_primary_map!B:B, ""), XLOOKUP(B3:B1000, rakuten_fact_daily_raw!B3:B1000, rakuten_fact_daily_raw!D3:D1000, "") ) )} -> item_001 | E3: {=IF(B3:B1000="",,XLOOKUP(B3:B1000, rakuten_fact_daily_raw!B3:B1000, rakuten_fact_daily_raw!E3:E1000, ""))} -> ワイヤレスイヤホン Pro | F3: {=IF(B3:B1000="",,MAX(rakuten_fact_daily_raw!A3:A1000))} -> 45991 | G3: =IFERROR(__xludf.DUMMYFUNCTION("MAP(B3:B1000, LAMBDA(j, IF(j="""",, LET(asof, MAX(rakuten_fact_daily_raw!A3:A1000), IFERROR(MAX(FILTER(rakuten_fact_daily_raw!J3:J1000, rakuten_fact_daily_raw!B3:B1000=j, rakuten_fact_daily_raw!A3:A1000=asof)), """") ) ) )) "),5000.0) -> 5000 | H3: =IFERROR(__xludf.DUMMYFUNCTION("MAP(B3:B1000, LAMBDA(j, IF(j="""",, LET(asof, MAX(rakuten_fact_daily_raw!A3:A1000), IFERROR(MAX(FILTER(rakuten_fact_daily_raw!T3:T1000, rakuten_fact_daily_raw!B3:B1000=j, rakuten_fact_daily_raw!A3:A1000=asof)), """") ) ) )) "),420.0) -> 420 | I3: =IFERROR(__xludf.DUMMYFUNCTION("MAP(B3:B1000, LAMBDA(j, IF(j="""",, LET(asof, MAX(rakuten_fact_daily_raw!A3:A1000), cnt, FILTER(rakuten_fact_daily_raw!V3:V1000, rakuten_fact_daily_raw!B3:B1000=j, rakuten_fact_daily_raw!A3:A1000=asof), rat, FILTER(rakuten_fact_daily_raw"&"!U3:U1000, rakuten_fact_daily_raw!B3:B1000=j, rakuten_fact_daily_raw!A3:A1000=asof), IFERROR(SUMPRODUCT(rat,cnt)/SUM(cnt), """") ) ) )) "),3.8) -> 3.8 | J3: =IFERROR(__xludf.DUMMYFUNCTION("MAP(B3:B1000, LAMBDA(j, IF(j="""",, LET(asof, MAX(rakuten_fact_daily_raw!A3:A1000), IFERROR(SUM(FILTER(rakuten_fact_daily_raw!V3:V1000, rakuten_fact_daily_raw!B3:B1000=j, rakuten_fact_daily_raw!A3:A1000=asof)), """") ) ) )) "),179.0) -> 179 | K3: =IFERROR(__xludf.DUMMYFUNCTION("MAP(B3:B1000, LAMBDA(j, IF(j="""",, LET(asof, MAX(rakuten_fact_daily_raw!A3:A1000), IFERROR(MIN(FILTER(rakuten_fact_daily_raw!W3:W1000, rakuten_fact_daily_raw!B3:B1000=j, rakuten_fact_daily_raw!A3:A1000=asof)), """") ) ) )) "),2.0) -> 2 | L3: =IFERROR(__xludf.DUMMYFUNCTION("MAP(B3:B1000, LAMBDA(j, IF(j="""",, LET(asof, MAX(rakuten_fact_daily_raw!A3:A1000), IFERROR(INDEX(FILTER(rakuten_fact_daily_raw!X3:X1000, rakuten_fact_daily_raw!B3:B1000=j, rakuten_fact_daily_raw!A3:A1000=asof),1), """") ) ) )) "),"ワイヤレスイヤホン") -> ワイヤレスイヤホン | M3: =IFERROR(__xludf.DUMMYFUNCTION("MAP(B3:B1000, LAMBDA(j, IF(j="""",, LET(asof, MAX(rakuten_fact_daily_raw!A3:A1000), IFERROR(INDEX(FILTER(rakuten_fact_daily_raw!Y3:Y1000, rakuten_fact_daily_raw!B3:B1000=j, rakuten_fact_daily_raw!A3:A1000=asof),1), """") ) ) )) "),4.0) -> 4 | N3: {=IF(B3:B1000="",,XLOOKUP(B3:B1000, rakuten_summary_7d!A3:A1000, rakuten_summary_7d!H3:H1000, ""))} | O3: {=IF(B3:B1000="",,XLOOKUP(B3:B1000, rakuten_summary_7d!A3:A1000, rakuten_summary_7d!G3:G1000, ""))} | P3: {=IF(B3:B1000="",,XLOOKUP(B3:B1000, rakuten_summary_7d!A3:A1000, rakuten_summary_7d!E3:E1000, ""))} | Q3: {=IF(B3:B1000="",,XLOOKUP(B3:B1000, rakuten_summary_7d!A3:A1000, rakuten_summary_7d!F3:F1000, ""))} | R3: {=IF(B3:B1000="",,IFERROR(Q3:Q1000/P3:P1000,""))} | S3: {=IF(B3:B1000="",,IFERROR(N3:N1000/Q3:Q1000,""))} | T3: {=IF(B3:B1000="",,XLOOKUP(B3:B1000, rakuten_summary_7d!A3:A1000, rakuten_summary_7d!I3:I1000, ""))} | U3: {=IF(B3:B1000="",,XLOOKUP(B3:B1000, rakuten_summary_7d!A3:A1000, rakuten_summary_7d!J3:J1000, ""))} | V3: {=IF(B3:B1000="",,XLOOKUP(B3:B1000, rakuten_summary_7d!A3:A1000, rakuten_summary_7d!K3:K1000, ""))} | W3: {=IF(B3:B1000="",,XLOOKUP(B3:B1000, rakuten_summary_7d!A3:A1000, rakuten_summary_7d!M3:M1000, ""))} | X3: {=IF(B3:B1000="",,XLOOKUP(B3:B1000, rakuten_summary_7d!A3:A1000, rakuten_summary_7d!M3:M1000, ""))} | Y3: {=IF(B3:B1000="",,IFERROR(X3:X1000/W3:W1000,""))} | Z3: {=IF(B3:B1000="",,IFERROR(X3:X1000/W3:W1000,""))} | AA3: {=IF(B3:B1000="",,XLOOKUP(B3:B1000, rakuten_summary_7d!A3:A1000, rakuten_summary_7d!N3:N1000, ""))} | AB3: {=IF(B3:B1000="",,XLOOKUP(B3:B1000, rakuten_summary_7d!A3:A1000, rakuten_summary_7d!O3:O1000, ""))} | AC3: {=IF(B3:B1000="",,XLOOKUP(B3:B1000, rakuten_summary_7d!A3:A1000, rakuten_summary_7d!P3:P1000, ""))} | AD3: {=IF(B3:B1000="",,XLOOKUP(B3:B1000, rakuten_summary_7d!A3:A1000, rakuten_summary_7d!Q3:Q1000, ""))} | AE3: {=IF(B3:B1000="",,IFERROR(N3:N1000 - AD3:AD1000 - AA3:AA1000 - AB3:AB1000 - AC3:AC1000 - W3:W1000 - U3:U1000 - T3:T1000 - V3:V1000,""))} -> 0 | AF3: {=IF(B3:B1000="",,IFERROR(AE3:AE1000/N3:N1000,""))} | AG3: {=IF(B3:B1000="",,IFERROR((N3:N1000 - T3:T1000 - U3:U1000)/O3:O1000,""))} | AH3: {=IF(B3:B1000="",,XLOOKUP(B3:B1000, rakuten_summary_30d!A3:A1000, rakuten_summary_30d!H3:H1000, ""))} -> 7900000 | AI3: {=IF(B3:B1000="",,XLOOKUP(B3:B1000, rakuten_summary_30d!A3:A1000, rakuten_summary_30d!G3:G1000, ""))} -> 1580 | AJ3: {=IF(B3:B1000="",,XLOOKUP(B3:B1000, rakuten_summary_30d!A3:A1000, rakuten_summary_30d!E3:E1000, ""))} -> 48422 | AK3: {=IF(B3:B1000="",,XLOOKUP(B3:B1000, rakuten_summary_30d!A3:A1000, rakuten_summary_30d!F3:F1000, ""))} -> 1465 | AL3: {=IF(B3:B1000="",,IFERROR(AK3:AK1000/AJ3:AJ1000,""))} -> 0.030254843 | AM3: {=IF(B3:B1000="",,IFERROR(AH3:AH1000/AK3:AK1000,""))} -> 5392.4915 | AN3: {=IF(B3:B1000="",,XLOOKUP(B3:B1000, rakuten_summary_30d!A3:A1000, rakuten_summary_30d!I3:I1000, ""))} -> 0 | AO3: {=IF(B3:B1000="",,XLOOKUP(B3:B1000, rakuten_summary_30d!A3:A1000, rakuten_summary_30d!J3:J1000, ""))} -> 79000 | AP3: {=IF(B3:B1000="",,XLOOKUP(B3:B1000, rakuten_summary_30d!A3:A1000, rakuten_summary_30d!K3:K1000, ""))} -> 29700 | AQ3: {=IF(B3:B1000="",,XLOOKUP(B3:B1000, rakuten_summary_30d!A3:A1000, rakuten_summary_30d!L3:L1000, ""))} -> 632000 | AR3: {=IF(B3:B1000="",,XLOOKUP(B3:B1000, rakuten_summary_30d!A3:A1000, rakuten_summary_30d!M3:M1000, ""))} -> 790000 | AS3: {=IF(B3:B1000="",,IFERROR(AR3:AR1000/AQ3:AQ1000,""))} -> 1.25 | AT3: {=IF(B3:B1000="",,IFERROR(AQ3:AQ1000/AH3:AH1000,""))} -> 0.08 | AU3: {=IF(B3:B1000="",,XLOOKUP(B3:B1000, rakuten_summary_30d!A3:A1000, rakuten_summary_30d!N3:N1000, ""))} -> 4740000 | AV3: {=IF(B3:B1000="",,XLOOKUP(B3:B1000, rakuten_summary_30d!A3:A1000, rakuten_summary_30d!O3:O1000, ""))} -> 732500 | AW3: {=IF(B3:B1000="",,XLOOKUP(B3:B1000, rakuten_summary_30d!A3:A1000, rakuten_summary_30d!P3:P1000, ""))} -> 0 | AX3: {=IF(B3:B1000="",,XLOOKUP(B3:B1000, rakuten_summary_30d!A3:A1000, rakuten_summary_30d!Q3:Q1000, ""))} -> 75000 | AY3: {=IF(B3:B1000="",,IFERROR(AH3:AH1000 - AX3:AX1000 - AU3:AU1000 - AV3:AV1000 - AW3:AW1000 - AQ3:AQ1000 - AO3:AO1000 - AN3:AN1000 - AP3:AP1000,""))} -> 1611800 | AZ3: {=IF(B3:B1000="",,IFERROR(AY3:AY1000/AH3:AH1000,""))} -> 0.20402532 | BA3: {=IF(B3:B1000="",,IFERROR((AH3:AH1000 - AN3:AN1000 - AO3:AO1000)/AI3:AI1000,""))} -> 4950
A4: {=rakuten_fact_daily_raw!A4} -> 45962 | B4: =IFERROR(__xludf.DUMMYFUNCTION("""COMPUTED_VALUE"""),4.512345678002E12) -> 4512345678002 | C4: SKU-B005 | D4: item_002 | E4: オーガニックコットンTシャツ | F4: 45991 | G4: =IFERROR(__xludf.DUMMYFUNCTION("""COMPUTED_VALUE"""),3000.0) -> 3000 | H4: =IFERROR(__xludf.DUMMYFUNCTION("""COMPUTED_VALUE"""),214.0) -> 214 | I4: =IFERROR(__xludf.DUMMYFUNCTION("""COMPUTED_VALUE"""),4.1) -> 4.1 | J4: =IFERROR(__xludf.DUMMYFUNCTION("""COMPUTED_VALUE"""),109.0) -> 109 | K4: =IFERROR(__xludf.DUMMYFUNCTION("""COMPUTED_VALUE"""),12.0) -> 12 | L4: =IFERROR(__xludf.DUMMYFUNCTION("""COMPUTED_VALUE"""),"Tシャツ メンズ") -> Tシャツ メンズ | M4: =IFERROR(__xludf.DUMMYFUNCTION("""COMPUTED_VALUE"""),8.0) -> 8 | AE4: 0 | AH4: 1758000 | AI4: 586 | AJ4: 25668 | AK4: 544 | AL4: 0.021193704 | AM4: 3231.6176 | AN4: 0 | AO4: 17580 | AP4: 6800 | AQ4: 140640 | AR4: 175800 | AS4: 1.25 | AT4: 0.08 | AU4: 1054800 | AV4: 272000 | AW4: 0 | AX4: 27000 | AY4: 239180 | AZ4: 0.13605233 | BA4: 2970
A5: {=rakuten_fact_daily_raw!A5} -> 45962 | B5: =IFERROR(__xludf.DUMMYFUNCTION("""COMPUTED_VALUE"""),4.512345678003E12) -> 4512345678003 | C5: SKU-C012 | D5: item_003 | E5: 国産コシヒカリ 5kg | F5: 45991 | G5: =IFERROR(__xludf.DUMMYFUNCTION("""COMPUTED_VALUE"""),3000.0) -> 3000 | H5: =IFERROR(__xludf.DUMMYFUNCTION("""COMPUTED_VALUE"""),214.0) -> 214 | I5: =IFERROR(__xludf.DUMMYFUNCTION("""COMPUTED_VALUE"""),4.6) -> 4.6 | J5: =IFERROR(__xludf.DUMMYFUNCTION("""COMPUTED_VALUE"""),329.0) -> 329 | K5: =IFERROR(__xludf.DUMMYFUNCTION("""COMPUTED_VALUE"""),3.0) -> 3 | L5: =IFERROR(__xludf.DUMMYFUNCTION("""COMPUTED_VALUE"""),"米 5kg") -> 米 5kg | M5: =IFERROR(__xludf.DUMMYFUNCTION("""COMPUTED_VALUE"""),1.0) -> 1 | AE5: 0 | AH5: 15858000 | AI5: 5286 | AJ5: 93910 | AK5: 4775 | AL5: 0.050846555 | AM5: 3321.0471 | AN5: 0 | AO5: 158580 | AP5: 148200 | AQ5: 1268640 | AR5: 792900 | AS5: 0.625 | AT5: 0.08 | AU5: 9514800 | AV5: 2387500 | AW5: 0 | AX5: 54000 | AY5: 2326280 | AZ5: 0.14669441 | BA5: 2970
A6: {=rakuten_fact_daily_raw!A6} -> 45962 | B6: =IFERROR(__xludf.DUMMYFUNCTION("""COMPUTED_VALUE"""),4.512345678004E12) -> 4512345678004 | C6: SKU-D030 | D6: item_004 | E6: ビタミンC美容液 | F6: 45991 | G6: =IFERROR(__xludf.DUMMYFUNCTION("""COMPUTED_VALUE"""),3000.0) -> 3000 | H6: =IFERROR(__xludf.DUMMYFUNCTION("""COMPUTED_VALUE"""),356.0) -> 356 | I6: =IFERROR(__xludf.DUMMYFUNCTION("""COMPUTED_VALUE"""),3.6000000000000005) -> 3.6 | J6: =IFERROR(__xludf.DUMMYFUNCTION("""COMPUTED_VALUE"""),89.0) -> 89 | K6: =IFERROR(__xludf.DUMMYFUNCTION("""COMPUTED_VALUE"""),11.0) -> 11 | L6: =IFERROR(__xludf.DUMMYFUNCTION("""COMPUTED_VALUE"""),"美容液") -> 美容液 | M6: =IFERROR(__xludf.DUMMYFUNCTION("""COMPUTED_VALUE"""),10.0) -> 10 | AE6: 0 | AH6: 1032000 | AI6: 344 | AJ6: 18851 | AK6: 324 | AL6: 0.017187417 | AM6: 3185.1852 | AN6: 0 | AO6: 10320 | AP6: 5800 | AQ6: 82560 | AR6: 154800 | AS6: 1.875 | AT6: 0.08 | AU6: 619200 | AV6: 162000 | AW6: 0 | AX6: 18000 | AY6: 134120 | AZ6: 0.12996124 | BA6: 2970
A7: {=rakuten_fact_daily_raw!A7} -> 45962 | B7: =IFERROR(__xludf.DUMMYFUNCTION("""COMPUTED_VALUE"""),4.512345678005E12) -> 4512345678005 | C7: SKU-E099 | D7: item_005 | E7: 超軽量キャンプチェア | F7: 45991 | G7: =IFERROR(__xludf.DUMMYFUNCTION("""COMPUTED_VALUE"""),4500.0) -> 4500 | H7: =IFERROR(__xludf.DUMMYFUNCTION("""COMPUTED_VALUE"""),39.0) -> 39 | I7: =IFERROR(__xludf.DUMMYFUNCTION("""COMPUTED_VALUE"""),4.2) -> 4.2 | J7: =IFERROR(__xludf.DUMMYFUNCTION("""COMPUTED_VALUE"""),34.0) -> 34 | K7: =IFERROR(__xludf.DUMMYFUNCTION("""COMPUTED_VALUE"""),36.0) -> 36 | L7: =IFERROR(__xludf.DUMMYFUNCTION("""COMPUTED_VALUE"""),"アウトドアチェア") -> アウトドアチェア | M7: =IFERROR(__xludf.DUMMYFUNCTION("""COMPUTED_VALUE"""),32.0) -> 32 | AE7: 0 | AH7: 49500 | AI7: 11 | AJ7: 1560 | AK7: 11 | AL7: 0.0070512821 | AM7: 4500 | AN7: 0 | AO7: 495 | AP7: 0 | AQ7: 3960 | AR7: 11000 | AS7: 2.7777778 | AT7: 0.08 | AU7: 29700 | AV7: 5500 | AW7: 0 | AX7: 60000 | AY7: -50155 | AZ7: -1.0132323 | BA7: 4455
A153: {=rakuten_fact_daily_raw!A153}
A154: {=rakuten_fact_daily_raw!A154}
A155: {=rakuten_fact_daily_raw!A155}
A156: {=rakuten_fact_daily_raw!A156}
A157: {=rakuten_fact_daily_raw!A157}
A158: {=rakuten_fact_daily_raw!A158}
A159: {=rakuten_fact_daily_raw!A159}
A160: {=rakuten_fact_daily_raw!A160}
A161: {=rakuten_fact_daily_raw!A161}
A162: {=rakuten_fact_daily_raw!A162}
A163: {=rakuten_fact_daily_raw!A163}
A164: {=rakuten_fact_daily_raw!A164}
... A1000: {=rakuten_fact_daily_raw!A1000}

Sheet rakuten_master
A1: Jan | B1: aku | C1: rakuten_item_i

Sheet rakuten_fact_daily_raw
A1: date | B1: jan | C1: sku | D1: rakuten_item_id | E1: item_name | F1: sessions | G1: orders | H1: units_sold | I1: sales_net | J1: selling_price | K1: discount_amount | L1: points_amount | M1: coupon_issue_fee | N1: ad_spend | O1: ad_sales | P1: platform_fee | Q1: shipping_cost | R1: other_fee | S1: cogs | T1: stock_quantity | U1: review_rating | V1: review_count | W1: genre_rank | X1: search_rank_keyword | Y1: search_rank_position | Z1: cvr | AA1: aov | AB1: effective_price_per_unit | AC1: effective_discount_rate | AD1: gross_profit_incl_tax | AE1: profit_margin | AF1: roas | AG1: tacos
A2: 日付 | B2: JAN | C2: SKU | D2: 楽天商品ID | E2: 商品名 | F2: アクセス | G2: 注文件数 | H2: 販売数 | I2: 売上(税込) | J2: 販売価格(税込) | K2: 値引額 | L2: ポイント原資 | M2: クーポン手数料 | N2: 広告費 | O2: 広告売上 | P2: 手数料 | Q2: 送料負担 | R2: その他費 | S2: 原価 | T2: 在庫数 | U2: 評価 | V2: レビュー数 | W2: ジャンル順位 | X2: 検索KW | Y2: 検索順位 | Z2: CVR | AA2: 客単価 | AB2: 実質単価 | AC2: 実質値引率 | AD2: 粗利(税込) | AE2: 粗利率 | AF2: ROAS | AG2: TACoS
A3: 45962 | B3: 4512345678001 | C3: SKU-A001 | D3: item_001 | E3: ワイヤレスイヤホン Pro | F3: 1646 | G3: 49 | H3: 56 | I3: 280000 | J3: 5000 | K3: 0 | L3: 2800 | M3: 4900 | N3: 22400 | O3: 28000 | P3: 168000 | Q3: 24500 | R3: 0 | S3: 2500 | T3: 444 | U3: 3.8 | V3: 150 | W3: 5 | X3: ワイヤレスイヤホン | Y3: 1
A4: 45962 | B4: 4512345678002 | C4: SKU-B005 | D4: item_002 | E4: オーガニックコットンTシャツ | F4: 1107 | G4: 29 | H4: 32 | I4: 96000 | J4: 3000 | K4: 0 | L4: 960 | M4: 0 | N4: 7680 | O4: 9600 | P4: 57600 | Q4: 14500 | R4: 0 | S4: 900 | T4: 268 | U4: 4.2 | V4: 80 | W4: 10 | X4: Tシャツ メンズ | Y4: 12
A5: 45962 | B5: 4512345678003 | C5: SKU-C012 | D5: item_003 | E5: 国産コシヒカリ 5kg | F5: 3118 | G5: 163 | H5: 174 | I5: 522000 | J5: 3000 | K5: 0 | L5: 5220 | M5: 16300 | N5: 41760 | O5: 26100 | P5: 313200 | Q5: 81500 | R5: 0 | S5: 1800 | T5: 826 | U5: 3.5 | V5: 300 | W5: 1 | X5: 米 5kg | Y5: 1
A6: 45962 | B6: 4512345678004 | C6: SKU-D030 | D6: item_004 | E6: ビタミンC美容液 | F6: 817 | G6: 11 | H6: 12 | I6: 36000 | J6: 3000 | K6: 0 | L6: 360 | M6: 1100 | N6: 2880 | O6: 5400 | P6: 21600 | Q6: 5500 | R6: 0 | S6: 600 | T6: 188 | U6: 4.5 | V6: 60 | W6: 16 | X6: 美容液 | Y6: 10
A7: 45962 | B7: 4512345678005 | C7: SKU-E099 | D7: item_005 | E7: 超軽量キャンプチェア | F7: 64 | G7: 0 | H7: 0 | I7: 0 | J7: 4500 | K7: 0 | L7: 0 | M7: 0 | N7: 0 | O7: 500 | P7: 0 | Q7: 0 | R7: 0 | S7: 2000 | T7: 50 | U7: 3.8 | V7: 5 | W7: 32 | X7: アウトドアチェア | Y7: 35
A8: 45963 | B8: 4512345678001 | C8: SKU-A001 | D8: item_001 | E8: ワイヤレスイヤホン Pro | F8: 1477 | G8: 45 | H8: 50 | I8: 250000 | J8: 5000 | K8: 0 | L8: 2500 | M8: 0 | N8: 20000 | O8: 25000 | P8: 150000 | Q8: 22500 | R8: 0 | S8: 2500 | T8: 394 | U8: 4 | V8: 151 | W8: 6 | X8: ワイヤレスイヤホン | Y8: 5
A9: 45963 | B9: 4512345678002 | C9: SKU-B005 | D9: item_002 | E9: オーガニックコットンTシャツ | F9: 874 | G9: 20 | H9: 21 | I9: 63000 | J9: 3000 | K9: 0 | L9: 630 | M9: 0 | N9: 5040 | O9: 6300 | P9: 37800 | Q9: 10000 | R9: 0 | S9: 900 | T9: 247 | U9: 4.2 | V9: 81 | W9: 8 | X9: Tシャツ メンズ | Y9: 5
A10: 45963 | B10: 4512345678003 | C10: SKU-C012 | D10: item_003 | E10: 国産コシヒカリ 5kg | F10: 3218 | G10: 182 | H10: 206 | I10: 618000 | J10: 3000 | K10: 0 | L10: 6180 | M10: 0 | N10: 49440 | O10: 30900 | P10: 370800 | Q10: 91000 | R10: 0 | S10: 1800 | T10: 620 | U10: 4.7 | V10: 301 | W10: 1 | X10: 米 5kg | Y10: 1
A11: 45963 | B11: 4512345678004 | C11: SKU-D030 | D11: item_004 | E11: ビタミンC美容液 | F11: 837 | G11: 16 | H11: 16 | I11: 48000 | J11: 3000 | K11: 0 | L11: 480 | M11: 0 | N11: 3840 | O11: 7200 | P11: 28800 | Q11: 8000 | R11: 0 | S11: 600 | T11: 172 | U11: 4.4 | V11: 61 | W11: 13 | X11: 美容液 | Y11: 20
A12: 45963 | B12: 4512345678005 | C12: SKU-E099 | D12: item_005 | E12: 超軽量キャンプチェア | F12: 70 | G12: 0 | H12: 0 | I12: 0 | J12: 4500 | K12: 0 | L12: 0 | M12: 0 | N12: 0 | O12: 500 | P12: 0 | Q12: 0 | R12: 0 | S12: 2000 | T12: 50 | U12: 3.5 | V12: 6 | W12: 33 | X12: アウトドアチェア | Y12: 34
A13: 45964 | B13: 4512345678001 | C13: SKU-A001 | D13: item_001 | E13: ワイヤレスイヤホン Pro | F13: 1746 | G13: 46 | H13: 48 | I13: 240000 | J13: 5000 | K13: 0 | L13: 2400 | M13: 4600 | N13: 19200 | O13: 24000 | P13: 144000 | Q13: 23000 | R13: 0 | S13: 2500 | T13: 346 | U13: 4.5 | V13: 152 | W13: 1 | X13: ワイヤレスイヤホン | Y13: 6
A14: 45964 | B14: 4512345678002 | C14: SKU-B005 | D14: item_002 | E14: オーガニックコットンTシャツ | F14: 743 | G14: 22 | H14: 23 | I14: 69000 | J14: 3000 | K14: 0 | L14: 690 | M14: 0 | N14: 5520 | O14: 6900 | P14: 41400 | Q14: 11000 | R14: 0 | S14: 900 | T14: 224 | U14: 3.9 | V14: 82 | W14: 12 | X14: Tシャツ メンズ | Y14: 4
... A152: 45991 | B152: 4512345678005 | C152: SKU-E099 | D152: item_005 | E152: 超軽量キャンプチェア | F152: 50 | G152: 1 | H152: 1 | I152: 4500 | J152: 4500 | K152: 0 | L152: 45 | M152: 0 | N152: 360 | O152: 0 | P152: 2700 | Q152: 500 | R152: 0 | S152: 2000 | T152: 39 | U152: 4.2 | V152: 34 | W152: 36 | X152: アウトドアチェア | Y152: 32

Sheet rakuten_fact_daily_calc
A1: jan | B1: cvr | C1: aov | D1: effective_price_per_unit | E1: effective_discount_rate | F1: gross_profit_incl_tax | G1: profit_margin | H1: roas | I1: tacos
A2: JAN | B2: CVR | C2: 客単価 | D2: 実質単価 | E2: 実質値引率 | F2: 粗利(税込) | G2: 粗利率 | H2: ROAS | I2: TACoS
B3: 0.024316109

Sheet rakuten_summary_7d
A1: Jan | B1: sku | C1: rakuten_item_id | D1: item_name | E1: as_of_date | F1: stock_quantity_latest | G1: review_rating_latest | H1: review_count_latest | I1: genre_rank_latest | J1: search_rank_keyword_latest | K1: search_rank_position_latest | L1: sales_net_7d | M1: units_sold_7d | N1: sessions_7d | O1: orders_7d | P1: cvr_7d | Q1: aov_7d | R1: discount_amount_7d | S1: points_amount_7d | T1: coupon_issue_fee_7d | U1: ad_spend_7d | V1: ad_sales_7d | W1: roas_7d | X1: tacos_7d | Y1: platform_fee_7d | Z1: shipping_cost_7d | AA1: other_fee_7d | AB1: cogs_7d | AC1: gross_profit_7d | AD1: profit_margin_7d | AE1: effective_revenue_per_unit_7d
A2: JANコード | B2: SKU | C2: 楽天商品ID | D2: 商品名 | E2: 基準日 | F2: 在庫数(最新) | G2: 評価(最新) | H2: レビュー数(最新) | I2: ジャンル順位(最新) | J2: 検索KW(最新) | K2: 検索順位(最新) | L2: 売上(込)_7日 | M2: 販売数_7日 | N2: アクセス_7日 | O2: 注文件数_7日 | P2: CVR_7日 | Q2: 客単価_7日 | R2: 値引額_7日 | S2: ポイント原資_7日 | T2: クーポン手数料_7日 | U2: 広告費_7日 | V2: 広告売上_7日 | W2: ROAS_7日 | X2: TACoS_7日 | Y2: 手数料_7日 | Z2: 送料負担_7日 | AA2: その他費_7日 | AB2: 原価_7日 | AC2: 粗利(税込)_7日 | AD2: 粗利率_7日 | AE2: 実質売上/個_7日
A3: =IFERROR(__xludf.DUMMYFUNCTION("SORT(UNIQUE(FILTER(rakuten_fact_daily_raw!B3:B1000, rakuten_fact_daily_raw!B3:B1000<>""""))) "),4.512345678001E12) -> 4512345678001 | B3: =IFERROR(__xludf.DUMMYFUNCTION("LET( v_hdr, rakuten_view!A1:ZZ1, v_data, rakuten_view!A2:ZZ1000, jan_in, TO_TEXT(A3:A1000), v_jan, TO_TEXT(INDEX(v_data,,MATCH(""Jan"", v_hdr, 0))), v_sku, INDEX(v_data,,MATCH(""sku"", v_hdr, 0)), MAP(jan_in, LAMBDA(j, IF(j="""","""""&", IFERROR(XLOOKUP(j, v_jan, v_sku, """"), """")) )) ) "),"")
A4: =IFERROR(__xludf.DUMMYFUNCTION("""COMPUTED_VALUE"""),4.512345678002E12) -> 4512345678002
A5: =IFERROR(__xludf.DUMMYFUNCTION("""COMPUTED_VALUE"""),4.512345678003E12) -> 4512345678003
A6: =IFERROR(__xludf.DUMMYFUNCTION("""COMPUTED_VALUE"""),4.512345678004E12) -> 4512345678004
A7: =IFERROR(__xludf.DUMMYFUNCTION("""COMPUTED_VALUE"""),4.512345678005E12) -> 4512345678005

Sheet rakuten_summary_30d
A1: Jan | B1: sku | C1: rakuten_item_id | D1: item_name | E1: as_of_date | F1: stock_quantity_latest | G1: review_rating_latest | H1: review_count_latest | I1: genre_rank_latest | J1: search_rank_keyword_latest | K1: search_rank_position_latest | L1: sales_net_30d | M1: units_sold_30d | N1: sessions_30d | O1: orders_30d | P1: cvr_30d | Q1: aov_30d | R1: discount_amount_30d | S1: points_amount_30d | T1: coupon_issue_fee_30d | U1: ad_spend_30d | V1: ad_sales_30d | W1: roas_30d | X1: tacos_30d | Y1: platform_fee_30d | Z1: shipping_cost_30d | AA1: other_fee_30d | AB1: cogs_30d | AC1: gross_profit_30d | AD1: profit_margin_30d | AE1: effective_revenue_per_unit_30d
A2: JANコード | B2: SKU | C2: 楽天商品ID | D2: 商品名 | E2: 基準日 | F2: 在庫数(最新) | G2: 評価(最新) | H2: レビュー数(最新) | I2: ジャンル順位(最新) | J2: 検索KW(最新) | K2: 検索順位(最新) | L2: 売上(込)_30日 | M2: 販売数_30日 | N2: アクセス_30日 | O2: 注文件数_30日 | P2: CVR_30日 | Q2: 客単価_30日 | R2: 値引額_30日 | S2: ポイント原資_30日 | T2: クーポン手数料_30日 | U2: 広告費_30日 | V2: 広告売上_30日 | W2: ROAS_30日 | X2: TACoS_30日 | Y2: 手数料_30日 | Z2: 送料負担_30日 | AA2: その他費_30日 | AB2: 原価_30日 | AC2: 粗利(税込)_30日 | AD2: 粗利率_30日 | AE2: 実質売上/個_30日
A3: =IFERROR(__xludf.DUMMYFUNCTION("LET( asof, MAX(rakuten_fact_daily_raw!A3:A1000), start, asof-29, r, FILTER(rakuten_fact_daily_raw!A3:Y1000, rakuten_fact_daily_raw!A3:A1000>=start), QUERY( r, ""select Col2, max(Col3), max(Col4), max(Col5), sum(Col6), sum(Col7)"&", sum(Col8), sum(Col9), sum(Col11), sum(Col12), sum(Col13), sum(Col14), sum(Col15), sum(Col16), sum(Col17), sum(Col18), sum(Col19) where Col2 is not null group by Col2 label Col2 'jan', max("&"Col3) 'sku', max(Col4) 'rakuten_item_id', max(Col5) 'item_name', sum(Col6) 'sessions_30d', sum(Col7) 'orders_30d', sum(Col8) 'units_sold_30d', sum(Col9) 'sales_net_30d', sum(Col11) 'discount_amount_30d', "&" sum(Col12) 'points_amount_30d', sum(Col13) 'coupon_issue_fee_30d', sum(Col14) 'ad_spend_30d', sum(Col15) 'ad_sales_30d', sum(Col16) 'platform_fee_30d', sum(Col17) 'shipping_cost_30d', sum(Col18) 'other_fee_30"&"d', sum(Col19) 'cogs_30d'"", 0 ) ) "),"jan") -> jan | B3: =IFERROR(__xludf.DUMMYFUNCTION("""COMPUTED_VALUE"""),"sku") -> sku | C3: =IFERROR(__xludf.DUMMYFUNCTION("""COMPUTED_VALUE"""),"rakuten_item_id") -> rakuten_item_id | D3: =IFERROR(__xludf.DUMMYFUNCTION("""COMPUTED_VALUE"""),"item_name") -> item_name | E3: =IFERROR(__xludf.DUMMYFUNCTION("""COMPUTED_VALUE"""),"sessions_30d") -> sessions_30d | F3: =IFERROR(__xludf.DUMMYFUNCTION("""COMPUTED_VALUE"""),"orders_30d") -> orders_30d | G3: =IFERROR(__xludf.DUMMYFUNCTION("""COMPUTED_VALUE"""),"units_sold_30d") -> units_sold_30d | H3: =IFERROR(__xludf.DUMMYFUNCTION("""COMPUTED_VALUE"""),"sales_net_30d") -> sales_net_30d | I3: =IFERROR(__xludf.DUMMYFUNCTION("""COMPUTED_VALUE"""),"discount_amount_30d") -> discount_amount_30d | J3: =IFERROR(__xludf.DUMMYFUNCTION("""COMPUTED_VALUE"""),"points_amount_30d") -> points_amount_30d | K3: =IFERROR(__xludf.DUMMYFUNCTION("""COMPUTED_VALUE"""),"coupon_issue_fee_30d") -> coupon_issue_fee_30d | L3: =IFERROR(__xludf.DUMMYFUNCTION("""COMPUTED_VALUE"""),"ad_spend_30d") -> ad_spend_30d | M3: =IFERROR(__xludf.DUMMYFUNCTION("""COMPUTED_VALUE"""),"ad_sales_30d") -> ad_sales_30d | N3: =IFERROR(__xludf.DUMMYFUNCTION("""COMPUTED_VALUE"""),"platform_fee_30d") -> platform_fee_30d | O3: =IFERROR(__xludf.DUMMYFUNCTION("""COMPUTED_VALUE"""),"shipping_cost_30d") -> shipping_cost_30d | P3: =IFERROR(__xludf.DUMMYFUNCTION("""COMPUTED_VALUE"""),"other_fee_30d") -> other_fee_30d | Q3: =IFERROR(__xludf.DUMMYFUNCTION("""COMPUTED_VALUE"""),"cogs_30d") -> cogs_30d
A4: =IFERROR(__xludf.DUMMYFUNCTION("""COMPUTED_VALUE"""),4.512345678001E12) -> 4512345678001 | B4: =IFERROR(__xludf.DUMMYFUNCTION("""COMPUTED_VALUE"""),"SKU-A001") -> SKU-A001 | C4: =IFERROR(__xludf.DUMMYFUNCTION("""COMPUTED_VALUE"""),"item_001") -> item_001 | D4: =IFERROR(__xludf.DUMMYFUNCTION("""COMPUTED_VALUE"""),"ワイヤレスイヤホン Pro") -> ワイヤレスイヤホン Pro | E4: =IFERROR(__xludf.DUMMYFUNCTION("""COMPUTED_VALUE"""),48422.0) -> 48422 | F4: =IFERROR(__xludf.DUMMYFUNCTION("""COMPUTED_VALUE"""),1465.0) -> 1465 | G4: =IFERROR(__xludf.DUMMYFUNCTION("""COMPUTED_VALUE"""),1580.0) -> 1580 | H4: =IFERROR(__xludf.DUMMYFUNCTION("""COMPUTED_VALUE"""),7900000.0) -> 7900000 | I4: =IFERROR(__xludf.DUMMYFUNCTION("""COMPUTED_VALUE"""),0.0) -> 0 | J4: =IFERROR(__xludf.DUMMYFUNCTION("""COMPUTED_VALUE"""),79000.0) -> 79000 | K4: =IFERROR(__xludf.DUMMYFUNCTION("""COMPUTED_VALUE"""),29700.0) -> 29700 | L4: =IFERROR(__xludf.DUMMYFUNCTION("""COMPUTED_VALUE"""),632000.0) -> 632000 | M4: =IFERROR(__xludf.DUMMYFUNCTION("""COMPUTED_VALUE"""),790000.0) -> 790000 | N4: =IFERROR(__xludf.DUMMYFUNCTION("""COMPUTED_VALUE"""),4740000.0) -> 4740000 | O4: =IFERROR(__xludf.DUMMYFUNCTION("""COMPUTED_VALUE"""),732500.0) -> 732500 | P4: =IFERROR(__xludf.DUMMYFUNCTION("""COMPUTED_VALUE"""),0.0) -> 0 | Q4: =IFERROR(__xludf.DUMMYFUNCTION("""COMPUTED_VALUE"""),75000.0) -> 75000
A5: =IFERROR(__xludf.DUMMYFUNCTION("""COMPUTED_VALUE"""),4.512345678002E12) -> 4512345678002 | B5: =IFERROR(__xludf.DUMMYFUNCTION("""COMPUTED_VALUE"""),"SKU-B005") -> SKU-B005 | C5: =IFERROR(__xludf.DUMMYFUNCTION("""COMPUTED_VALUE"""),"item_002") -> item_002 | D5: =IFERROR(__xludf.DUMMYFUNCTION("""COMPUTED_VALUE"""),"オーガニックコットンTシャツ") -> オーガニックコットンTシャツ | E5: =IFERROR(__xludf.DUMMYFUNCTION("""COMPUTED_VALUE"""),25668.0) -> 25668 | F5: =IFERROR(__xludf.DUMMYFUNCTION("""COMPUTED_VALUE"""),544.0) -> 544 | G5: =IFERROR(__xludf.DUMMYFUNCTION("""COMPUTED_VALUE"""),586.0) -> 586 | H5: =IFERROR(__xludf.DUMMYFUNCTION("""COMPUTED_VALUE"""),1758000.0) -> 1758000 | I5: =IFERROR(__xludf.DUMMYFUNCTION("""COMPUTED_VALUE"""),0.0) -> 0 | J5: =IFERROR(__xludf.DUMMYFUNCTION("""COMPUTED_VALUE"""),17580.0) -> 17580 | K5: =IFERROR(__xludf.DUMMYFUNCTION("""COMPUTED_VALUE"""),6800.0) -> 6800 | L5: =IFERROR(__xludf.DUMMYFUNCTION("""COMPUTED_VALUE"""),140640.0) -> 140640 | M5: =IFERROR(__xludf.DUMMYFUNCTION("""COMPUTED_VALUE"""),175800.0) -> 175800 | N5: =IFERROR(__xludf.DUMMYFUNCTION("""COMPUTED_VALUE"""),1054800.0) -> 1054800 | O5: =IFERROR(__xludf.DUMMYFUNCTION("""COMPUTED_VALUE"""),272000.0) -> 272000 | P5: =IFERROR(__xludf.DUMMYFUNCTION("""COMPUTED_VALUE"""),0.0) -> 0 | Q5: =IFERROR(__xludf.DUMMYFUNCTION("""COMPUTED_VALUE"""),27000.0) -> 27000
A6: =IFERROR(__xludf.DUMMYFUNCTION("""COMPUTED_VALUE"""),4.512345678003E12) -> 4512345678003 | B6: =IFERROR(__xludf.DUMMYFUNCTION("""COMPUTED_VALUE"""),"SKU-C012") -> SKU-C012 | C6: =IFERROR(__xludf.DUMMYFUNCTION("""COMPUTED_VALUE"""),"item_003") -> item_003 | D6: =IFERROR(__xludf.DUMMYFUNCTION("""COMPUTED_VALUE"""),"国産コシヒカリ 5kg") -> 国産コシヒカリ 5kg | E6: =IFERROR(__xludf.DUMMYFUNCTION("""COMPUTED_VALUE"""),93910.0) -> 93910 | F6: =IFERROR(__xludf.DUMMYFUNCTION("""COMPUTED_VALUE"""),4775.0) -> 4775 | G6: =IFERROR(__xludf.DUMMYFUNCTION("""COMPUTED_VALUE"""),5286.0) -> 5286 | H6: =IFERROR(__xludf.DUMMYFUNCTION("""COMPUTED_VALUE"""),1.5858E7) -> 15858000 | I6: =IFERROR(__xludf.DUMMYFUNCTION("""COMPUTED_VALUE"""),0.0) -> 0 | J6: =IFERROR(__xludf.DUMMYFUNCTION("""COMPUTED_VALUE"""),158580.0) -> 158580 | K6: =IFERROR(__xludf.DUMMYFUNCTION("""COMPUTED_VALUE"""),148200.0) -> 148200 | L6: =IFERROR(__xludf.DUMMYFUNCTION("""COMPUTED_VALUE"""),1268640.0) -> 1268640 | M6: =IFERROR(__xludf.DUMMYFUNCTION("""COMPUTED_VALUE"""),792900.0) -> 792900 | N6: =IFERROR(__xludf.DUMMYFUNCTION("""COMPUTED_VALUE"""),9514800.0) -> 9514800 | O6: =IFERROR(__xludf.DUMMYFUNCTION("""COMPUTED_VALUE"""),2387500.0) -> 2387500 | P6: =IFERROR(__xludf.DUMMYFUNCTION("""COMPUTED_VALUE"""),0.0) -> 0 | Q6: =IFERROR(__xludf.DUMMYFUNCTION("""COMPUTED_VALUE"""),54000.0) -> 54000
A7: =IFERROR(__xludf.DUMMYFUNCTION("""COMPUTED_VALUE"""),4.512345678004E12) -> 4512345678004 | B7: =IFERROR(__xludf.DUMMYFUNCTION("""COMPUTED_VALUE"""),"SKU-D030") -> SKU-D030 | C7: =IFERROR(__xludf.DUMMYFUNCTION("""COMPUTED_VALUE"""),"item_004") -> item_004 | D7: =IFERROR(__xludf.DUMMYFUNCTION("""COMPUTED_VALUE"""),"ビタミンC美容液") -> ビタミンC美容液 | E7: =IFERROR(__xludf.DUMMYFUNCTION("""COMPUTED_VALUE"""),18851.0) -> 18851 | F7: =IFERROR(__xludf.DUMMYFUNCTION("""COMPUTED_VALUE"""),324.0) -> 324 | G7: =IFERROR(__xludf.DUMMYFUNCTION("""COMPUTED_VALUE"""),344.0) -> 344 | H7: =IFERROR(__xludf.DUMMYFUNCTION("""COMPUTED_VALUE"""),1032000.0) -> 1032000 | I7: =IFERROR(__xludf.DUMMYFUNCTION("""COMPUTED_VALUE"""),0.0) -> 0 | J7: =IFERROR(__xludf.DUMMYFUNCTION("""COMPUTED_VALUE"""),10320.0) -> 10320 | K7: =IFERROR(__xludf.DUMMYFUNCTION("""COMPUTED_VALUE"""),5800.0) -> 5800 | L7: =IFERROR(__xludf.DUMMYFUNCTION("""COMPUTED_VALUE"""),82560.0) -> 82560 | M7: =IFERROR(__xludf.DUMMYFUNCTION("""COMPUTED_VALUE"""),154800.0) -> 154800 | N7: =IFERROR(__xludf.DUMMYFUNCTION("""COMPUTED_VALUE"""),619200.0) -> 619200 | O7: =IFERROR(__xludf.DUMMYFUNCTION("""COMPUTED_VALUE"""),162000.0) -> 162000 | P7: =IFERROR(__xludf.DUMMYFUNCTION("""COMPUTED_VALUE"""),0.0) -> 0 | Q7: =IFERROR(__xludf.DUMMYFUNCTION("""COMPUTED_VALUE"""),18000.0) -> 18000
A8: =IFERROR(__xludf.DUMMYFUNCTION("""COMPUTED_VALUE"""),4.512345678005E12) -> 4512345678005 | B8: =IFERROR(__xludf.DUMMYFUNCTION("""COMPUTED_VALUE"""),"SKU-E099") -> SKU-E099 | C8: =IFERROR(__xludf.DUMMYFUNCTION("""COMPUTED_VALUE"""),"item_005") -> item_005 | D8: =IFERROR(__xludf.DUMMYFUNCTION("""COMPUTED_VALUE"""),"超軽量キャンプチェア") -> 超軽量キャンプチェア | E8: =IFERROR(__xludf.DUMMYFUNCTION("""COMPUTED_VALUE"""),1560.0) -> 1560 | F8: =IFERROR(__xludf.DUMMYFUNCTION("""COMPUTED_VALUE"""),11.0) -> 11 | G8: =IFERROR(__xludf.DUMMYFUNCTION("""COMPUTED_VALUE"""),11.0) -> 11 | H8: =IFERROR(__xludf.DUMMYFUNCTION("""COMPUTED_VALUE"""),49500.0) -> 49500 | I8: =IFERROR(__xludf.DUMMYFUNCTION("""COMPUTED_VALUE"""),0.0) -> 0 | J8: =IFERROR(__xludf.DUMMYFUNCTION("""COMPUTED_VALUE"""),495.0) -> 495 | K8: =IFERROR(__xludf.DUMMYFUNCTION("""COMPUTED_VALUE"""),0.0) -> 0 | L8: =IFERROR(__xludf.DUMMYFUNCTION("""COMPUTED_VALUE"""),3960.0) -> 3960 | M8: =IFERROR(__xludf.DUMMYFUNCTION("""COMPUTED_VALUE"""),11000.0) -> 11000 | N8: =IFERROR(__xludf.DUMMYFUNCTION("""COMPUTED_VALUE"""),29700.0) -> 29700 | O8: =IFERROR(__xludf.DUMMYFUNCTION("""COMPUTED_VALUE"""),5500.0) -> 5500 | P8: =IFERROR(__xludf.DUMMYFUNCTION("""COMPUTED_VALUE"""),0.0) -> 0 | Q8: =IFERROR(__xludf.DUMMYFUNCTION("""COMPUTED_VALUE"""),60000.0) -> 60000

Sheet config
A1: config_key | B1: config_value | C1: config_type | D1: scope | E1: description | F1: updated_at | G1: updated_by | H1: notes
A2: 設定キー | B2: 設定値 | C2: 型 | D2: 適用範囲 | E2: 説明 | F2: 更新日時 | G2: 更新者 | H2: メモ
